tidy_twitter/__init__.py
tidy_twitter/cli.py
tidy_twitter/twitter_cleanup.py
tidy_twitter-1.1.2.dist-info/entry_points.txt
tidy_twitter-1.1.2.dist-info/LICENSE.txt
tidy_twitter-1.1.2.dist-info/WHEEL
tidy_twitter-1.1.2.dist-info/METADATA
tidy_twitter-1.1.2.dist-info/RECORD
